[{"id":"55f7fbe90e5befa8","type":"tab","label":"[trigger] msg.delay overrides the configured delay","disabled":false,"info":"if the delay is set on the message than it overrides the setting on the node.\n\nThe test works by setting the trigger delay to 250ms but the message contains an override of 500ms. The delay causes the payload to arrive 150ms before the second mesage at the join, hence the result: 0,3,1.","env":[]},{"id":"63f121bc487d6b45","type":"inject","z":"55f7fbe90e5befa8","name":"inject delay of 500ms","props":[{"p":"delay","v":"500","vt":"num"},{"p":"payload"}],"repeat":"","crontab":"","once":false,"onceDelay":0.1,"topic":"","payload":"3","payloadType":"num","x":223,"y":314.375,"wires":[["f4dafcd62665a8f6","347a01391caf18a2"]]},{"id":"f4dafcd62665a8f6","type":"trigger","z":"55f7fbe90e5befa8","name":"","op1":"1","op2":"0","op1type":"num","op2type":"num","duration":"250","extend":false,"overrideDelay":true,"units":"ms","reset":"","bytopic":"all","topic":"topic","outputs":1,"x":551,"y":314.375,"wires":[["2388adccf44b289b"]]},{"id":"2388adccf44b289b","type":"join","z":"55f7fbe90e5befa8","name":"","mode":"custom","build":"array","property":"payload","propertyType":"msg","key":"topic","joiner":"\\n","joinerType":"str","useparts":false,"accumulate":false,"timeout":"","count":"3","reduceRight":false,"reduceExp":"","reduceInit":"","reduceInitType":"","reduceFixup":"","x":858,"y":314.375,"wires":[["2c300f57dd1b48f2","fc8f767f505193f1"]]},{"id":"2c300f57dd1b48f2","type":"ut-assert-values","z":"55f7fbe90e5befa8","name":"","rules":[{"p":"payload","pt":"msg","t":"eql","to":"[1,3,0]","tot":"json"}],"x":1186,"y":314.375,"wires":[[]]},{"id":"347a01391caf18a2","type":"delay","z":"55f7fbe90e5befa8","name":"","pauseType":"delay","timeout":"350","timeoutUnits":"milliseconds","rate":"1","nbRateUnits":"1","rateUnits":"second","randomFirst":"1","randomLast":"5","randomUnits":"seconds","drop":false,"allowrate":false,"outputs":1,"x":621.25,"y":380,"wires":[["2388adccf44b289b"]]},{"id":"3cc773c305da2c34","type":"ut-assert-status","z":"55f7fbe90e5befa8","name":"","nodeid":"f4dafcd62665a8f6","content":"","colour":"blue","shape":"dot","inverse":false,"x":618.75,"y":225,"wires":[]},{"id":"fc8f767f505193f1","type":"debug","z":"55f7fbe90e5befa8","name":"debug 5","active":true,"tosidebar":true,"console":false,"tostatus":false,"complete":"false","statusVal":"","statusType":"auto","x":1201,"y":234.5,"wires":[]}]